electrify/__init__.py
electrify/cli.py
electrify/commands/__init__.py
electrify/commands/channel/DownloadAttachments.py
electrify/commands/channel/HelloWorld.py
electrify/commands/channel/__init__.py
electrify/commands/channel/base.py
electrify/commands/ticket/HelloWorld.py
electrify/commands/ticket/__init__.py
electrify/commands/ticket/base.py
electrify_cli-0.1.0.dist-info/METADATA
electrify_cli-0.1.0.dist-info/WHEEL
electrify_cli-0.1.0.dist-info/entry_points.txt
electrify_cli-0.1.0.dist-info/top_level.txt
electrify_cli-0.1.0.dist-info/RECORD
